pyconfig_handler/__init__.py
simple_config_handler-0.0.3.dist-info/METADATA
simple_config_handler-0.0.3.dist-info/WHEEL
simple_config_handler-0.0.3.dist-info/top_level.txt
simple_config_handler-0.0.3.dist-info/RECORD
