Metadata-Version: 2.1
Name: simple_config_handler
Version: 0.0.3
Summary: A simple config handler for python
Author: Justin Rose
Author-email: rosejustin601@gmail.com
License: MIT
Classifier: Programming Language :: Python :: 3
Classifier: License :: OSI Approved :: MIT License
Classifier: Operating System :: OS Independent
Requires-Python: >=3.6
